pypardot/__init__.py
pypardot/client.py
pypardot/errors.py
pypardot/objects/__init__.py
pypardot/objects/accounts.py
pypardot/objects/campaigns.py
pypardot/objects/customfields.py
pypardot/objects/customredirects.py
pypardot/objects/dynamiccontent.py
pypardot/objects/emailclicks.py
pypardot/objects/emails.py
pypardot/objects/emailtemplates.py
pypardot/objects/forms.py
pypardot/objects/importapi.py
pypardot/objects/lifecyclehistories.py
pypardot/objects/lifecyclestages.py
pypardot/objects/listmemberships.py
pypardot/objects/lists.py
pypardot/objects/opportunities.py
pypardot/objects/prospectaccounts.py
pypardot/objects/prospects.py
pypardot/objects/tagobjects.py
pypardot/objects/tags.py
pypardot/objects/users.py
pypardot/objects/visitoractivities.py
pypardot/objects/visitors.py
pypardot/objects/visits.py
pypardot/objects_v3/__init__.py
pypardot/objects_v3/accounts.py
pypardot/objects_v3/campaigns.py
pypardot/objects_v3/emails.py
pypardot/objects_v3/importapi.py
pypardot/objects_v3/lists.py
pypardot/objects_v3/opportunities.py
pypardot/objects_v3/prospects.py
pypardot/objects_v3/users.py
pypardot/objects_v3/visitoractivities.py
pypardot/objects_v3/visitors.py
pypardot/objects_v3/visits.py
PyPardotSF-0.1.1.dist-info/AUTHORS.md
PyPardotSF-0.1.1.dist-info/LICENSE
PyPardotSF-0.1.1.dist-info/METADATA
PyPardotSF-0.1.1.dist-info/WHEEL
PyPardotSF-0.1.1.dist-info/top_level.txt
PyPardotSF-0.1.1.dist-info/RECORD
