Metadata-Version: 2.1
Name: PyPardotSF
Version: 0.1.1
Summary: API wrapper for API v3 & v4 of Pardot marketing automation software.
Home-page: https://github.com/anelendata/PyPardotSF
Author: Daigo Tanaka, Anelen Co., LLC
License: UNKNOWN
Keywords: pardot
Platform: UNKNOWN
Classifier: Development Status :: 4 - Beta
Classifier: License :: OSI Approved :: MIT License
Classifier: Operating System :: MacOS :: MacOS X
Classifier: Operating System :: POSIX :: Linux
Classifier: Programming Language :: Python :: 3.6
Classifier: Programming Language :: Python :: 3.7
Classifier: Programming Language :: Python :: 3.8
License-File: LICENSE
License-File: AUTHORS.md
Requires-Dist: requests
